{"chunk_definitions":[{"row":8,"row_count":1,"visible":true,"expansion_state":0,"options":{"engine":"r","label":"setup","include":false},"document_id":"F254782D","chunk_id":"csetup_chunk","chunk_label":"setup"},{"row":24,"row_count":1,"visible":true,"expansion_state":0,"options":{"engine":"r","label":"unnamed-chunk-34"},"document_id":"F254782D","chunk_id":"c7umfzsramjs8","chunk_label":"unnamed-chunk-1"},{"row":49,"row_count":1,"visible":true,"expansion_state":0,"options":{"engine":"r","label":"unnamed-chunk-27"},"document_id":"F254782D","chunk_id":"cp9o2bgsjdy27","chunk_label":"unnamed-chunk-2"},{"row":62,"row_count":1,"visible":true,"expansion_state":0,"options":{"engine":"r","label":"unnamed-chunk-28"},"document_id":"F254782D","chunk_id":"ch0rj31nyd0me","chunk_label":"unnamed-chunk-3"},{"row":83,"row_count":1,"visible":true,"expansion_state":0,"options":{"engine":"r","label":"unnamed-chunk-21"},"document_id":"F254782D","chunk_id":"c67ukzge86klu","chunk_label":"unnamed-chunk-4"},{"row":104,"row_count":1,"visible":true,"expansion_state":0,"options":{"engine":"r","label":"unnamed-chunk-52"},"document_id":"F254782D","chunk_id":"csc2prxszk6av","chunk_label":"unnamed-chunk-5"},{"row":129,"row_count":1,"visible":true,"expansion_state":0,"options":{"engine":"r","label":"unnamed-chunk-61"},"document_id":"F254782D","chunk_id":"csja4m1i48g36","chunk_label":"unnamed-chunk-6"},{"row":142,"row_count":1,"visible":true,"expansion_state":0,"options":{"engine":"r","label":"unnamed-chunk-75"},"document_id":"F254782D","chunk_id":"cl235rdu5dtgm","chunk_label":"unnamed-chunk-7"}],"doc_write_time":1651258199,"working_dir":null,"default_chunk_options":{"echo":false}}